{"trial_id": "03", "hyperparameters": {"space": [{"class_name": "Boolean", "config": {"name": "batch_norm", "default": false, "conditions": []}}, {"class_name": "Float", "config": {"name": "dropout", "default": 0.0, "conditions": [], "min_value": 0.0, "max_value": 0.2, "step": 0.03, "sampling": null}}, {"class_name": "Choice", "config": {"name": "learning_rate", "default": 2e-05, "conditions": [], "values": [2e-05, 8e-05, 0.0002], "ordered": true}}, {"class_name": "Choice", "config": {"name": "epsilon", "default": 1e-08, "conditions": [], "values": [1e-08, 5e-08, 1e-07], "ordered": true}}], "values": {"batch_norm": false, "dropout": 0.18, "learning_rate": 8e-05, "epsilon": 5e-08}}, "metrics": {"metrics": {"loss": {"direction": "min", "observations": [{"value": [0.21154799312353134], "step": 0}]}, "categorical_accuracy": {"direction": "max", "observations": [{"value": [0.9167096018791199], "step": 0}]}, "top_k_categorical_accuracy": {"direction": "min", "observations": [{"value": [0.9988837540149689], "step": 0}]}, "val_loss": {"direction": "min", "observations": [{"value": [0.27151164412498474], "step": 0}]}, "val_categorical_accuracy": {"direction": "max", "observations": [{"value": [0.9038652181625366], "step": 0}]}, "val_top_k_categorical_accuracy": {"direction": "min", "observations": [{"value": [0.9970267415046692], "step": 0}]}}}, "score": 0.27151164412498474, "best_step": 0, "status": "COMPLETED"}